doc_mcp_server-0.1.2.dist-info/licenses/LICENSE
document_analyzer/__init__.py
document_analyzer/server.py
document_analyzer/analyzers/__init__.py
document_analyzer/analyzers/base.py
document_analyzer/analyzers/excel_analyzer.py
doc_mcp_server-0.1.2.dist-info/METADATA
doc_mcp_server-0.1.2.dist-info/WHEEL
doc_mcp_server-0.1.2.dist-info/entry_points.txt
doc_mcp_server-0.1.2.dist-info/top_level.txt
doc_mcp_server-0.1.2.dist-info/RECORD
