Metadata-Version: 2.4
Name: doc-mcp-server
Version: 0.1.2
Summary: 让AI读懂任何复杂文档 - MCP服务器
Author-email: Yang Jiahui <jiahuide0320@gmail.com>
License: MIT
Project-URL: Homepage, https://github.com/jiahuidegit/doc-mcp-server
Project-URL: Documentation, https://github.com/jiahuidegit/doc-mcp-server#readme
Project-URL: Repository, https://github.com/jiahuidegit/doc-mcp-server
Project-URL: Issues, https://github.com/jiahuidegit/doc-mcp-server/issues
Keywords: mcp,document,excel,pdf,ai,llm
Classifier: Development Status :: 3 - Alpha
Classifier: Intended Audience :: Developers
Classifier: License :: OSI Approved :: MIT License
Classifier: Programming Language :: Python :: 3
Classifier: Programming Language :: Python :: 3.10
Classifier: Programming Language :: Python :: 3.11
Classifier: Programming Language :: Python :: 3.12
Requires-Python: >=3.10
License-File: LICENSE
Requires-Dist: mcp>=0.1.0
Requires-Dist: openpyxl>=3.1.0
Requires-Dist: python-docx>=1.1.0
Requires-Dist: PyPDF2>=3.0.0
Requires-Dist: pdfplumber>=0.10.0
Provides-Extra: dev
Requires-Dist: pytest>=7.4.0; extra == "dev"
Requires-Dist: pytest-asyncio>=0.21.0; extra == "dev"
Requires-Dist: black>=23.0.0; extra == "dev"
Requires-Dist: mypy>=1.5.0; extra == "dev"
Provides-Extra: vector
Requires-Dist: sentence-transformers>=2.2.0; extra == "vector"
Requires-Dist: chromadb>=0.4.0; extra == "vector"
Dynamic: license-file
